dsblocks/__init__.py
dsblocks/_modidx.py
dsblocks/blocks/__init__.py
dsblocks/blocks/blocks.py
dsblocks/blocks/huggingface.py
dsblocks/blocks/preprocessing.py
dsblocks/config/__init__.py
dsblocks/config/bt_defaults.py
dsblocks/core/__init__.py
dsblocks/core/callback.py
dsblocks/core/components.py
dsblocks/core/compose.py
dsblocks/core/data_conversion.py
dsblocks/core/utils.py
dsblocks/datasets/__init__.py
dsblocks/datasets/datasets.py
dsblocks/utils/__init__.py
dsblocks/utils/cli.py
dsblocks/utils/dummies.py
dsblocks/utils/nbdev_utils.py
dsblocks/utils/session.py
dsblocks/utils/test_exporter.py
dsblocks/utils/utils.py
tests/__init__.py
tests/blocks/__init__.py
tests/blocks/test_blocks.py
tests/blocks/test_preprocessing.py
tests/config/__init__.py
tests/config/test_bt_defaults.py
tests/core/__init__.py
tests/core/test_callback.py
tests/core/test_components.py
tests/core/test_compose.py
tests/core/test_data_conversion.py
tests/core/test_utils.py
tests/datasets/__init__.py
tests/datasets/test_datasets.py
tests/utils/__init__.py
tests/utils/test_cli.py
tests/utils/test_dummies.py
tests/utils/test_nbdev_utils.py
tests/utils/test_session.py
tests/utils/test_test_exporter.py
tests/utils/test_utils.py
dsblocks-0.0.15.dist-info/LICENSE
dsblocks-0.0.15.dist-info/METADATA
dsblocks-0.0.15.dist-info/WHEEL
dsblocks-0.0.15.dist-info/entry_points.txt
dsblocks-0.0.15.dist-info/top_level.txt
dsblocks-0.0.15.dist-info/RECORD
