Metadata-Version: 2.1
Name: dsblocks
Version: 0.0.15
Summary: DS Blocks
Home-page: https://github.com/Jaume-JCI/ds-blocks
Author: Jaume Amores
Author-email: jamorej@jci.com
License: Apache Software License 2.0
Keywords: nbdev jupyter notebook python
Classifier: Development Status :: 4 - Beta
Classifier: Intended Audience :: Developers
Classifier: Natural Language :: English
Classifier: Programming Language :: Python :: 3.7
Classifier: Programming Language :: Python :: 3.8
Classifier: Programming Language :: Python :: 3.9
Classifier: Programming Language :: Python :: 3.10
Classifier: License :: OSI Approved :: Apache Software License
Requires-Python: >=3.7,<=3.12
License-File: LICENSE
Requires-Dist: pandas
Requires-Dist: scikit-learn
Requires-Dist: pyarrow
Requires-Dist: numpy
Requires-Dist: ipython
Requires-Dist: matplotlib
Requires-Dist: graphviz
Requires-Dist: optuna
Requires-Dist: ipynbname
Requires-Dist: tensorflow
Requires-Dist: rich
Requires-Dist: hpsearch
Provides-Extra: dev
Requires-Dist: pytest ; extra == 'dev'
Requires-Dist: pytest-cov ; extra == 'dev'
Requires-Dist: ipdb ; extra == 'dev'
Requires-Dist: jupyter ; extra == 'dev'
Requires-Dist: ipykernel ; extra == 'dev'
Provides-Extra: linux
Requires-Dist: sh ; extra == 'linux'
